[   
    {
        "id": "1",
        "name": "DNI-DRIVER LICENCE",
            "description":"",     "created_at":"",     "updated_at":""
    },
    {
        "id": "2",
        "name": "DRIVER LICENCE",
            "description":"",     "created_at":"",     "updated_at":""
    },
    {
        "id": "3",
        "name": "PASSPORT",
            "description":"",     "created_at":"",     "updated_at":""
    },
    {
        "id": "4",
        "name": "SERVICE-TDC",
            "description":"",     "created_at":"",     "updated_at":""
    },
    {
        "id": "5",
        "name": "SELFIE",
            "description":"",     "created_at":"",     "updated_at":""
    },
    {
        "id": "6",
        "name": "NAME COMPANY",
            "description":"",     "created_at":"",     "updated_at":""
    },
    {
        "id": "7",
        "name": "VAT",
            "description":"",     "created_at":"",     "updated_at":""
    },
    {
        "id": "8",
        "name": "COMPANY SOCIAL STATUS",
            "description":"",     "created_at":"",     "updated_at":""
    },
    {
        "id": "9",
        "name": "ACCOUNT BANK DETAIL",
            "description":"",     "created_at":"",     "updated_at":""
    },
    {
        "id": "10",
        "name": "DECLARATION FOUND",
            "description":"",     "created_at":"",     "updated_at":""
    },
    {
        "id": "11",
        "name": "DECLARATION FOUND EXPOSED",
            "description":"",     "created_at":"",     "updated_at":""
    },
    {
        "id": "12",
        "name": "COMMERCIAL BANK-COMMERCIAL REFERENCE",
            "description":"",     "created_at":"",     "updated_at":""
    },
    {
        "id": "13",
        "name": "COMPANY MERCANTIL TRANSLATE",
            "description":"",     "created_at":"",     "updated_at":""
    }
]